xSide_Terminal/__init__.py
xSide_Terminal/plugin.cp311-win_amd64.pyd
xSide_Terminal/plugin.pyi
xSide_Terminal/webengine.cp311-win_amd64.pyd
xSide_Terminal/webengine.pyi
xSide_Terminal/xtermsrv/__init__.py
xSide_Terminal/xtermsrv/xtermsrv.py
xSide_Terminal/xtermsrv/api/__init__.py
xSide_Terminal/xtermsrv/api/v1/__init__.py
xSide_Terminal/xtermsrv/api/v1/ptymgr.cp311-win_amd64.pyd
xSide_Terminal/xtermsrv/api/v1/ptymgr.pyi
xSide_Terminal/xtermsrv/api/v1/terminal.cp311-win_amd64.pyd
xSide_Terminal/xtermsrv/api/v1/terminal.pyi
xSide_Terminal/xtermsrv/static/bundle.js
xSide_Terminal/xtermsrv/static/index.html
xSide_Terminal/xtermsrv/static/assets/index-BoIVgL22.css
xside_terminal-2026.1.5a0.dist-info/METADATA
xside_terminal-2026.1.5a0.dist-info/WHEEL
xside_terminal-2026.1.5a0.dist-info/entry_points.txt
xside_terminal-2026.1.5a0.dist-info/top_level.txt
xside_terminal-2026.1.5a0.dist-info/RECORD
